python_logger/__init__.py
python_logger/json_logger.py
python_kibana_logger-0.1.2.dist-info/LICENSE
python_kibana_logger-0.1.2.dist-info/METADATA
python_kibana_logger-0.1.2.dist-info/WHEEL
python_kibana_logger-0.1.2.dist-info/RECORD
